README.md
setup.py
imgBoxDetector/__init__.py
imgBoxDetector/model.py
imgBoxDetector.egg-info/PKG-INFO
imgBoxDetector.egg-info/SOURCES.txt
imgBoxDetector.egg-info/dependency_links.txt
imgBoxDetector.egg-info/requires.txt
imgBoxDetector.egg-info/top_level.txt
imgBoxDetector/analysis/__init__.py
imgBoxDetector/analysis/visualize.py
imgBoxDetector/data/__init__.py
imgBoxDetector/data/dataset.py
imgBoxDetector/data/transforms/__init__.py
imgBoxDetector/data/transforms/blur.py
imgBoxDetector/data/transforms/crop.py
imgBoxDetector/data/transforms/flip.py
imgBoxDetector/data/transforms/rescale.py
imgBoxDetector/data/transforms/rotate.py