Metadata-Version: 2.1
Name: imgBoxDetector
Version: 1.0.3
Summary: A model to detect various objects in an image
Home-page: UNKNOWN
Author: Anish Sofat
Author-email: sofatanish16@gmail.com
License: GPLv3
Platform: UNKNOWN
Classifier: License :: OSI Approved :: GNU General Public License v3 (GPLv3)
Classifier: Programming Language :: Python :: 3
Classifier: Programming Language :: Python :: 3.8
